chainfactory/__init__.py
chainfactory/chains/__init__.py
chainfactory/chains/generate_mask_template.fctr
chainfactory/chains/generate_prompt_template.fctr
chainfactory/core/__init__.py
chainfactory/core/components.py
chainfactory/core/engine/__init__.py
chainfactory/core/engine/chainfactory_engine.py
chainfactory/core/engine/chainfactory_engine_config.py
chainfactory/core/factory.py
chainfactory/core/parsing/__init__.py
chainfactory/core/parsing/class_from_dict.py
chainfactory/core/types.py
chainfactory/core/utils.py
chainfactory/interfaces/__init__.py
chainfactory/interfaces/langchain/__init__.py
chainfactory/interfaces/llamaindex/__init__.py
chainfactory_py-0.0.16.dist-info/LICENSE
chainfactory_py-0.0.16.dist-info/METADATA
chainfactory_py-0.0.16.dist-info/WHEEL
chainfactory_py-0.0.16.dist-info/RECORD
