Metadata-Version: 2.1
Name: chainfactory-py
Version: 0.0.16
Summary: Structured LLM Inference with Easy Parallelism and Tool Calling
License: MIT
Author: Pankaj Garkoti
Author-email: garkotipankaj@gmail.com
Requires-Python: >=3.10,<4.0
Classifier: License :: OSI Approved :: MIT License
Classifier: Programming Language :: Python :: 3
Classifier: Programming Language :: Python :: 3.10
Classifier: Programming Language :: Python :: 3.11
Classifier: Programming Language :: Python :: 3.12
Classifier: Programming Language :: Python :: 3.13
Requires-Dist: cityhash (>=0.4.7,<0.5.0)
Requires-Dist: colorama (>=0.4.6,<0.5.0)
Requires-Dist: ipykernel (>=6.29.5,<7.0.0)
Requires-Dist: langchain (>=0.3.7,<0.4.0)
Requires-Dist: langchain-anthropic (>=0.3.0,<0.4.0)
Requires-Dist: langchain-experimental (>=0.3.3,<0.4.0)
Requires-Dist: langchain-ollama (>=0.2.0,<0.3.0)
Requires-Dist: langchain-openai (>=0.2.8,<0.3.0)
Requires-Dist: pyyaml (>=6.0.1,<7.0.0)
Requires-Dist: tiktoken (>=0.7.0,<0.8.0)
